vibeincrement/__init__.py
vibeincrement/ai.py
vibeincrement/py.typed
vibeincrement-0.1.0.dist-info/METADATA
vibeincrement-0.1.0.dist-info/WHEEL
vibeincrement-0.1.0.dist-info/licenses/LICENSE
vibeincrement-0.1.0.dist-info/RECORD
